text2tac/__init__.py
text2tac/transformer/__init__.py
text2tac/transformer/extract_package_based.py
text2tac/transformer/new_datasets_hg_transformer_cl.py
text2tac/transformer/predict_server.py
text2tac-1.0.1.dist-info/LICENSE
text2tac-1.0.1.dist-info/METADATA
text2tac-1.0.1.dist-info/WHEEL
text2tac-1.0.1.dist-info/entry_points.txt
text2tac-1.0.1.dist-info/top_level.txt
text2tac-1.0.1.dist-info/RECORD
