Metadata-Version: 2.1
Name: text2tac
Version: 1.0.1
Summary: text2tac converts text to actions
Author: Jelle Piepenbrock, Lasse Blaauwbroek, Mirek Olsak, Vasily Pestun, Jason Rute, Fidel I. Schaposnik Massolo
License: Apache License
Requires-Python: <3.11,>3.9
License-File: LICENSE
Requires-Dist: pytactician ==15.1
Requires-Dist: tqdm
Requires-Dist: numpy
Requires-Dist: fire
Requires-Dist: pycapnp
Requires-Dist: psutil
Requires-Dist: dataclasses-json
Requires-Dist: pyyaml
Requires-Dist: graphviz
Requires-Dist: transformers ==4.29.2
Requires-Dist: datasets
Requires-Dist: tokenizers
Requires-Dist: torch ==1.12.0
Requires-Dist: pandas
